ChosenAPI/__init__.py
ChosenAPI/Company/CompanyMainInfo.py
ChosenAPI/Company/CompanyMergeInfo.py
ChosenAPI/Company/__init__.py
ChosenAPI/Config/Headers.py
ChosenAPI/Config/RootPath.py
ChosenAPI/Config/__init__.py
ChosenAPI/DataImport/BalanceSheet.py
ChosenAPI/DataImport/BaseInformation.py
ChosenAPI/DataImport/Business_composition.py
ChosenAPI/DataImport/CashFlow.py
ChosenAPI/DataImport/ChangeToNum.py
ChosenAPI/DataImport/IncomeStatement.py
ChosenAPI/DataImport/__init__.py
ChosenAPI/DataImport/account_receivable.py
ChosenAPI/DataImport/accounts_payable.py
ChosenAPI/DataImport/administration_expense.py
ChosenAPI/DataImport/advance_payment.py
ChosenAPI/DataImport/advance_peceipts.py
ChosenAPI/DataImport/asset_deal_income.py
ChosenAPI/DataImport/asset_impairment_loss.py
ChosenAPI/DataImport/bill_receivable.py
ChosenAPI/DataImport/biological_assets.py
ChosenAPI/DataImport/bonds_payable.py
ChosenAPI/DataImport/cash_equivalents.py
ChosenAPI/DataImport/cash_flow_additional_information.py
ChosenAPI/DataImport/constru_in_process.py
ChosenAPI/DataImport/deferred_earning.py
ChosenAPI/DataImport/deferred_tax_assets_and_deferred_tax_liability.py
ChosenAPI/DataImport/development_expenditure.py
ChosenAPI/DataImport/dividend_payable.py
ChosenAPI/DataImport/dividend_receivable.py
ChosenAPI/DataImport/employee_situation.py
ChosenAPI/DataImport/estimate_liability.py
ChosenAPI/DataImport/fair_value_variable_income.py
ChosenAPI/DataImport/financial_expense.py
ChosenAPI/DataImport/fixed_assets.py
ChosenAPI/DataImport/foreign_currency_monetary_items.py
ChosenAPI/DataImport/good_will.py
ChosenAPI/DataImport/government_subsidies.py
ChosenAPI/DataImport/hold_assets_for_sale.py
ChosenAPI/DataImport/hold_for_sale_assets.py
ChosenAPI/DataImport/hold_liabilities_for_sale.py
ChosenAPI/DataImport/hold_to_maturity_investments.py
ChosenAPI/DataImport/important_matters.py
ChosenAPI/DataImport/income_tax.py
ChosenAPI/DataImport/intangible_assets.py
ChosenAPI/DataImport/interest_payable.py
chosendata-1.0.2.dist-info/METADATA
chosendata-1.0.2.dist-info/WHEEL
chosendata-1.0.2.dist-info/top_level.txt
chosendata-1.0.2.dist-info/RECORD
